Workbook

Sheet Assumptions
A1: Operating Assumptions
A3: Driver | B3: Value | C3: Unit
A4: Starting customers | B4: 420 | C4: count
A5: Quarterly logo growth | B5: 0.18 | C5: rate
A6: Average revenue per account | B6: 1450 | C6: USD
A7: Quarterly gross churn | B7: 0.055 | C7: rate
A8: Gross margin | B8: 0.78 | C8: rate
A9: Sales and marketing per quarter | B9: 385000 | C9: USD
A10: Research and development per quarter | B10: 512000 | C10: USD
A11: General and administrative per quarter | B11: 194000 | C11: USD

Sheet Revenue
A1: Revenue Build
A3: FY2027 | B3: Q1 | C3: Q2 | D3: Q3 | E3: Q4 | F3: Total
A5: Customers | B5: =Assumptions!B4 | C5: =B5*(1+Assumptions!$B$5)*(1-Assumptions!$B$7) | D5: =C5*(1+Assumptions!$B$5)*(1-Assumptions!$B$7) | E5: =D5*(1+Assumptions!$B$5)*(1-Assumptions!$B$7)
A6: Bookings | B6: =B5*Assumptions!$B$6 | C6: =C5*Assumptions!$B$6 | D6: =D5*Assumptions!$B$6 | E6: =E5*Assumptions!$B$6
A8: Total Bookings | F8: =SUM(B6:E6)
A11: Expansion
A12: Expansion revenue | B12: =B6*Assumptions!$B$5 | C12: =C6*Assumptions!$B$5 | D12: =D6*Assumptions!$B$5 | E12: =E6*Assumptions!$B$5
A15: Quarterly revenue | B15: =B6+B12 | C15: =C6+C12 | D15: =D6+D12 | E15: =E6+E12
A16: Total Revenue | F16: =SUM(B15:E15)

Sheet PL
A1: Profit and Loss, FY2027
A3: Line item | B3: Note | C3: FY2027
A4: Revenue | C4: =Revenue!F16
A5: Cost of revenue | C5: =-C4*(1-0.71)
A6: Gross Profit | C6: =C4+C5
A7: Total Operating Expenses | C7: =Assumptions!B9*4+Assumptions!B10*4+Assumptions!B11*4
A8: Operating Income | C8: =C6-C7
A10: Net Margin | C10: =C6/C4
A12: Headline
A13: Ending ARR | C13: =Revenue!C12*4
A15: ARR (board figure) | C15: =Revenue!E6*4
